tftables.py
tftables-1.1.2.dist-info/DESCRIPTION.rst
tftables-1.1.2.dist-info/METADATA
tftables-1.1.2.dist-info/RECORD
tftables-1.1.2.dist-info/WHEEL
tftables-1.1.2.dist-info/metadata.json
tftables-1.1.2.dist-info/top_level.txt
