Metadata-Version: 2.0
Name: tftables
Version: 1.1.2
Summary: Interface for reading HDF5 files into Tensorflow.
Home-page: https://github.com/ghcollin/tftables
Author: ghcollin
Author-email: UNKNOWN
License: MIT
Keywords: tensorflow HDF5
Platform: UNKNOWN
Classifier: Development Status :: 4 - Beta
Classifier: Intended Audience :: Developers
Classifier: Intended Audience :: Science/Research
Classifier: License :: OSI Approved :: MIT License
Classifier: Programming Language :: Python :: 2.7
Classifier: Programming Language :: Python :: 3
Classifier: Topic :: Scientific/Engineering :: Mathematics
Classifier: Topic :: Software Development :: Libraries :: Python Modules
Requires-Dist: multitables
Requires-Dist: numpy (!=1.10.1)
Requires-Dist: tensorflow
